querystring_tag/__init__.py
querystring_tag/apps.py
querystring_tag/constants.py
querystring_tag/expressions.py
querystring_tag/parse_utils.py
querystring_tag/utils.py
querystring_tag/templatetags/__init__.py
querystring_tag/templatetags/querystring_tag.py
querystring_tag/templatetags/tests.py
django_querystring_tag-1.0.3.dist-info/LICENSE
django_querystring_tag-1.0.3.dist-info/METADATA
django_querystring_tag-1.0.3.dist-info/WHEEL
django_querystring_tag-1.0.3.dist-info/top_level.txt
django_querystring_tag-1.0.3.dist-info/RECORD
