Metadata-Version: 2.1
Name: django-querystring-tag
Version: 1.0.3
Author: Andy Babic
Author-email: andyjbabic@gmail.com
License: BSD-3-Clause
Keywords: django querystring GET parameters pagination filter state-preserving link template tag util
Classifier: Environment :: Web Environment
Classifier: Development Status :: 5 - Production/Stable
Classifier: Intended Audience :: Developers
Classifier: Operating System :: OS Independent
Classifier: License :: OSI Approved :: BSD License
Classifier: Natural Language :: English
Classifier: Programming Language :: Python
Classifier: Programming Language :: Python :: 3.7
Classifier: Programming Language :: Python :: 3.8
Classifier: Programming Language :: Python :: 3.9
Classifier: Framework :: Django
Classifier: Framework :: Django :: 3.1
Classifier: Framework :: Django :: 3.2
Classifier: Framework :: Django :: 4.0
Requires-Python: >=3.7
License-File: LICENSE
Requires-Dist: Django (>=3.1)
Provides-Extra: lint
Requires-Dist: black (==22.3.0) ; extra == 'lint'
Requires-Dist: isort (==5.9.3) ; extra == 'lint'
Requires-Dist: flake8 (==3.9.2) ; extra == 'lint'
Provides-Extra: test
Requires-Dist: pytest-cov (==2.12.1) ; extra == 'test'
Requires-Dist: pytest-mock (==3.6.1) ; extra == 'test'
Requires-Dist: pytest-django (==4.4.0) ; extra == 'test'
Requires-Dist: pytest (==6.2.4) ; extra == 'test'
